sshexpect/__init__.py
sshexpect/sshexpect.py
sshexpect-1.0.6.dist-info/LICENSE
sshexpect-1.0.6.dist-info/METADATA
sshexpect-1.0.6.dist-info/WHEEL
sshexpect-1.0.6.dist-info/top_level.txt
sshexpect-1.0.6.dist-info/RECORD
