Metadata-Version: 2.1
Name: sshexpect
Version: 1.0.6
Summary: pexpect for asyncssh and paramiko
Home-page: https://github.com/amadxx/sshexpect
Author: Dmytro Pavlyuk
Author-email: dmitry.pavluk@gmail.com
License: MIT
Platform: UNKNOWN
Classifier: License :: OSI Approved :: MIT License
Classifier: Programming Language :: Python :: 3
Classifier: Programming Language :: Python :: 3.8
Requires-Dist: pexpect
